pep8ext_naming.py
pep8_naming-0.14.1.dist-info/LICENSE
pep8_naming-0.14.1.dist-info/METADATA
pep8_naming-0.14.1.dist-info/WHEEL
pep8_naming-0.14.1.dist-info/entry_points.txt
pep8_naming-0.14.1.dist-info/top_level.txt
pep8_naming-0.14.1.dist-info/RECORD
