Metadata-Version: 2.1
Name: pep8-naming
Version: 0.14.1
Summary: Check PEP-8 naming conventions, plugin for flake8
Home-page: https://github.com/PyCQA/pep8-naming
Author: Florent Xicluna
Author-email: florent.xicluna@gmail.com
License: Expat license
Project-URL: Source, https://github.com/PyCQA/pep8-naming
Project-URL: Issues, https://github.com/PyCQA/pep8-naming/issues
Project-URL: Changelog, https://github.com/PyCQA/pep8-naming/blob/main/CHANGELOG.rst
Keywords: flake8 pep8 naming
Classifier: Development Status :: 5 - Production/Stable
Classifier: Environment :: Console
Classifier: Framework :: Flake8
Classifier: Intended Audience :: Developers
Classifier: License :: OSI Approved :: MIT License
Classifier: Operating System :: OS Independent
Classifier: Programming Language :: Python
Classifier: Programming Language :: Python :: 3
Classifier: Programming Language :: Python :: 3.8
Classifier: Programming Language :: Python :: 3.9
Classifier: Programming Language :: Python :: 3.10
Classifier: Programming Language :: Python :: 3.11
Classifier: Programming Language :: Python :: 3.12
Classifier: Programming Language :: Python :: 3 :: Only
Classifier: Topic :: Software Development :: Libraries :: Python Modules
Classifier: Topic :: Software Development :: Quality Assurance
Requires-Python: >=3.8
License-File: LICENSE
Requires-Dist: flake8>=5.0.0
